passa/__init__.py
passa/__main__.py
passa/_pip.py
passa/_pip_shims.py
passa/caches.py
passa/candidates.py
passa/cli.py
passa/dependencies.py
passa/dependencies_pip.py
passa/hashes.py
passa/lockers.py
passa/locking.py
passa/markers.py
passa/metadata.py
passa/projects.py
passa/providers.py
passa/reporters.py
passa/synchronizers.py
passa/traces.py
passa/utils.py
passa/vcs.py
passa/cli/__init__.py
passa/cli/_base.py
passa/cli/add.py
passa/cli/clean.py
passa/cli/freeze.py
passa/cli/install.py
passa/cli/lock.py
passa/cli/remove.py
passa/cli/sync.py
passa/cli/upgrade.py
passa/internals/__init__.py
passa/internals/_pip.py
passa/internals/_pip_shims.py
passa/internals/caches.py
passa/internals/candidates.py
passa/internals/dependencies.py
passa/internals/hashes.py
passa/internals/lockers.py
passa/internals/markers.py
passa/internals/metadata.py
passa/internals/providers.py
passa/internals/specifiers.py
passa/internals/synchronizers.py
passa/internals/traces.py
passa/internals/utils.py
passa/operations/__init__.py
passa/operations/_utils.py
passa/operations/lock.py
passa/operations/sync.py
passa/reporters/__init__.py
passa/reporters/base.py
passa/reporters/stdout.py
passa-0.3.0.dist-info/LICENSE.txt
passa-0.3.0.dist-info/METADATA
passa-0.3.0.dist-info/RECORD
passa-0.3.0.dist-info/WHEEL
passa-0.3.0.dist-info/entry_points.txt
passa-0.3.0.dist-info/top_level.txt
passa-0.3.0.dist-info/zip-safe
