Metadata-Version: 2.1
Name: passa
Version: 0.3.0
Summary: A resolver implementation for generating and interacting with Pipenv-compatible Lockfiles.
Home-page: https://github.com/sarugaku/passa
Author: Dan Ryan
Author-email: dan@danryan.co
License: ISC License
Keywords: dependency resolver,package management,package resolver,resolver,pip,pipenv,requirementslib,pipfile,dependencies,dependency management
Platform: UNKNOWN
Classifier: Development Status :: 4 - Beta
Classifier: License :: OSI Approved :: ISC License (ISCL)
Classifier: Operating System :: OS Independent
Classifier: Programming Language :: Python :: 2
Classifier: Programming Language :: Python :: 2.7
Classifier: Programming Language :: Python :: 3
Classifier: Programming Language :: Python :: 3.4
Classifier: Programming Language :: Python :: 3.5
Classifier: Programming Language :: Python :: 3.6
Classifier: Programming Language :: Python :: 3.7
Classifier: Topic :: Software Development :: Libraries :: Python Modules
Requires-Python: >=2.7,!=3.0,!=3.1,!=3.2,!=3.3
Provides-Extra: tests
Requires-Dist: appdirs
Requires-Dist: distlib
Requires-Dist: packaging
Requires-Dist: pip-shims (>=0.1.2)
Requires-Dist: plette[validation] (>=0.1.1)
Requires-Dist: requests
Requires-Dist: resolvelib (!=1.0.0.dev0,>=0.2.1)
Requires-Dist: requirementslib (>=1.1.1)
Requires-Dist: six
Requires-Dist: vistir (>=0.1.4)
Provides-Extra: tests
Requires-Dist: pytest-xdist; extra == 'tests'
Requires-Dist: pytest-timeout; extra == 'tests'
Requires-Dist: pytest-cov; extra == 'tests'
Requires-Dist: pytest; extra == 'tests'
